LICENCE
MANIFEST.in
README.rst
constants.py
setup.py
constants.egg-info/PKG-INFO
constants.egg-info/SOURCES.txt
constants.egg-info/dependency_links.txt
constants.egg-info/requires.txt
constants.egg-info/top_level.txt